myDynamixel/__init__.py
myDynamixel/myDynamixel.py
mydynamixel-3.1.1.dist-info/METADATA
mydynamixel-3.1.1.dist-info/WHEEL
mydynamixel-3.1.1.dist-info/top_level.txt
mydynamixel-3.1.1.dist-info/RECORD
